kb/__init__.py
kb/__main__.py
kb/cl_parser.py
kb/config.py
kb/db.py
kb/filesystem.py
kb/history.py
kb/initializer.py
kb/main.py
kb/opener.py
kb/styler.py
kb/viewer.py
kb/commands/__init__.py
kb/commands/add.py
kb/commands/delete.py
kb/commands/edit.py
kb/commands/erase.py
kb/commands/export.py
kb/commands/grep.py
kb/commands/ingest.py
kb/commands/search.py
kb/commands/sync.py
kb/commands/template.py
kb/commands/update.py
kb/commands/view.py
kb/entities/artifact.py
kb/printer/__init__.py
kb/printer/grep.py
kb/printer/search.py
kb/printer/style.py
kb/printer/template.py
kb_manager-0.1.8.dist-info/licenses/AUTHORS
kb_manager-0.1.8.dist-info/licenses/LICENSE
kb_manager-0.1.8.dist-info/METADATA
kb_manager-0.1.8.dist-info/WHEEL
kb_manager-0.1.8.dist-info/entry_points.txt
kb_manager-0.1.8.dist-info/top_level.txt
kb_manager-0.1.8.dist-info/RECORD
