Metadata-Version: 2.4
Name: kb-manager
Version: 0.1.8
Summary: A minimalist knowledge base manager
Home-page: https://github.com/gnebbia/kb
Download-URL: https://github.com/gnebbia/kb/archive/v0.1.8.tar.gz
Author: gnc
Author-email: nebbionegiuseppe@gmail.com
License: GPLv3
Keywords: kb
Platform: any
Classifier: Programming Language :: Python
Classifier: Programming Language :: Python :: 3
Classifier: Programming Language :: Python :: 3.6
Classifier: Programming Language :: Python :: 3.7
Classifier: Programming Language :: Python :: 3.8
Classifier: Programming Language :: Python :: 3.9
Classifier: Programming Language :: Python :: 3.10
Classifier: Operating System :: OS Independent
Requires-Python: >=3.6
License-File: LICENSE
License-File: AUTHORS
Requires-Dist: colored
Requires-Dist: toml
Requires-Dist: attr
Requires-Dist: attrs
Requires-Dist: gitpython
Dynamic: author
Dynamic: author-email
Dynamic: classifier
Dynamic: description
Dynamic: description-content-type
Dynamic: download-url
Dynamic: home-page
Dynamic: keywords
Dynamic: license
Dynamic: license-file
Dynamic: platform
Dynamic: requires-dist
Dynamic: requires-python
Dynamic: summary
